harupy/__init__.py
harupy/common.py
harupy/decorators.py
harupy/network.py
harupy/shell.py
harupy/text.py
harupy-1.4.3.dist-info/LICENSE
harupy-1.4.3.dist-info/METADATA
harupy-1.4.3.dist-info/WHEEL
harupy-1.4.3.dist-info/top_level.txt
harupy-1.4.3.dist-info/RECORD
