Metadata-Version: 2.1
Name: harupy
Version: 1.4.3
Summary: Library for handling Korean Hangul
Home-page: https://github.com/soo-kim/harupy
Author: Soo Kim
Author-email: sookim@outlook.jp
License: UNKNOWN
Download-URL: https://github.com/soo-kim/harupy/archive/1.3.tar.gz
Keywords: korean,hangul,string
Platform: UNKNOWN
Classifier: Programming Language :: Python :: 3
Classifier: Programming Language :: Python :: 3.2
Classifier: Programming Language :: Python :: 3.3
Classifier: Programming Language :: Python :: 3.4
Classifier: Programming Language :: Python :: 3.5
Classifier: Programming Language :: Python :: 3.6
Classifier: Programming Language :: Python :: 3.7
Requires-Python: >=3
